RasaHost/__init__.py
RasaHost/settings.py
RasaHost/controllers/__init__.py
RasaHost/controllers/analyze_controller.py
RasaHost/controllers/chat_controller.py
RasaHost/controllers/domain_controller.py
RasaHost/controllers/home_controller.py
RasaHost/controllers/logs_controller.py
RasaHost/controllers/models_controller.py
RasaHost/controllers/nlu_controller.py
RasaHost/controllers/rasa_controller.py
RasaHost/controllers/stories_controller.py
RasaHost/database/__init__.py
RasaHost/database/conversations.py
RasaHost/database/db_context.py
RasaHost/database/logs.py
RasaHost/database/metadata.py
RasaHost/logging/__init__.py
RasaHost/logging/db_handler.py
RasaHost/logging/filter.py
RasaHost/logging/request_id.py
RasaHost/logging/sender_id.py
RasaHost/logging/senderid_filter.py
RasaHost/logging/socketio_handler.py
RasaHost/models/__init__.py
RasaHost/models/azuretablestorage.py
RasaHost/models/factory.py
RasaHost/models/memory.py
RasaHost/models/mongodb.py
RasaHost/services/__init__.py
RasaHost/services/analyze_service.py
RasaHost/services/conversations_service.py
RasaHost/services/domain_service.py
RasaHost/services/logging_service.py
RasaHost/services/memoization_policy_service.py
RasaHost/services/nlu_service.py
RasaHost/services/query_parser.py
RasaHost/services/stories_service.py
RasaHost/static/content/bootstrap.css
RasaHost/static/content/bootstrap.min.css
RasaHost/static/content/site.css
RasaHost/static/fonts/glyphicons-halflings-regular.eot
RasaHost/static/fonts/glyphicons-halflings-regular.svg
RasaHost/static/fonts/glyphicons-halflings-regular.ttf
RasaHost/static/fonts/glyphicons-halflings-regular.woff
RasaHost/static/libs/modernizr-2.6.2.js
RasaHost/static/libs/respond.js
RasaHost/static/libs/respond.min.js
RasaHost/static/libs/autosize/autosize.js
RasaHost/static/libs/autosize/autosize.min.js
RasaHost/static/libs/bootstrap/css/bootstrap-grid.css
RasaHost/static/libs/bootstrap/css/bootstrap-grid.css.map
RasaHost/static/libs/bootstrap/css/bootstrap-grid.min.css
rasa_host-0.3.0.dist-info/LICENSE.txt
rasa_host-0.3.0.dist-info/METADATA
rasa_host-0.3.0.dist-info/WHEEL
rasa_host-0.3.0.dist-info/top_level.txt
rasa_host-0.3.0.dist-info/RECORD
